twh_parser/__init__.py
twh_parser/__main__.py
twh_parser/adults.py
twh_parser/config.py
twh_parser/config.toml
twh_parser/groups.py
twh_parser/load_all.py
twh_parser/merit_badge_parser.py
twh_parser/merit_badges.py
twh_parser/parser.py
twh_parser/ranks.py
twh_parser/scouts.py
twh_parser/signoffs.py
twh_parser/utils.py
twh_parser/data/adults.csv
twh_parser/data/mb_data.toml
twh_parser/data/mb_names.txt
twh_parser/data/merit_badge_signoffs.csv
twh_parser/data/merit_badges.csv
twh_parser/data/merit_badges.toml
twh_parser/data/rank_signoffs.csv
twh_parser/data/requirements.toml
twh_parser/data/scouts.csv
twh_parser-0.15.0.dist-info/METADATA
twh_parser-0.15.0.dist-info/WHEEL
twh_parser-0.15.0.dist-info/entry_points.txt
twh_parser-0.15.0.dist-info/licenses/LICENSE
twh_parser-0.15.0.dist-info/RECORD
