Metadata-Version: 2.3
Name: twh-parser
Version: 0.15.0
Summary: Parse Troopwebhost export files into TOML, YAML, or JSON
Project-URL: Repository, https://gitlab.com/troopmanager/twh_parser
Author-email: Michael Perkins <perkinsms@gmail.com>
Maintainer-email: Michael Perkins <perkinsms@gmail.com>
License: MIT License
License-File: LICENSE
Classifier: Development Status :: 4 - Beta
Classifier: License :: OSI Approved :: MIT License
Classifier: Programming Language :: Python :: 3
Classifier: Programming Language :: Python :: 3.9
Classifier: Programming Language :: Python :: 3.10
Classifier: Programming Language :: Python :: 3.11
Requires-Python: >3.9
Requires-Dist: click~=8.1
Requires-Dist: icecream
Requires-Dist: more-itertools
Requires-Dist: objexplore
Requires-Dist: python-dotenv
Requires-Dist: pyyaml~=6.0
Requires-Dist: toml~=0.10
